robotkernel/__init__.py
robotkernel/builders.py
robotkernel/builders_31.py
robotkernel/builders_32.py
robotkernel/completion_finders.py
robotkernel/constants.py
robotkernel/display.py
robotkernel/display_ipykernel.py
robotkernel/display_pyolite.py
robotkernel/exceptions.py
robotkernel/executors.py
robotkernel/install.py
robotkernel/kernel.py
robotkernel/listeners.py
robotkernel/monkeypatches.py
robotkernel/nbreader.py
robotkernel/selectors.py
robotkernel/selectors_white.py
robotkernel/utils.py
robotkernel/resources/kernel/kernel.js
robotkernel/resources/kernel/kernel.json
robotkernel/resources/kernel/logo-32x32.png
robotkernel/resources/kernel/logo-64x64.png
robotkernel/resources/notebooks/quickstart.ipynb
robotkernel/resources/notebooks/tutorial/00 JupyterLab User Interface.html
robotkernel/resources/notebooks/tutorial/00 Keyboard Shortcuts.ipynb
robotkernel/resources/notebooks/tutorial/00 What is the Jupyter Notebook.ipynb
robotkernel/resources/notebooks/tutorial/01 Running Code.ipynb
robotkernel/resources/notebooks/tutorial/02 Python XKCD.ipynb
robotkernel/resources/notebooks/tutorial/03 Running Robot.ipynb
robotkernel/resources/notebooks/tutorial/04 Robot XKCD.ipynb
robotkernel/resources/notebooks/tutorial/05 Interactive Selenium.ipynb
robotkernel/resources/notebooks/tutorial/06 Importing Notebooks.ipynb
robotkernel/resources/notebooks/tutorial/07 Prototyping Keywords.ipynb
robotkernel/resources/notebooks/tutorial/08 Interactive WhiteLibrary.ipynb
robotkernel/resources/notebooks/tutorial/09 Prototyping Libraries.ipynb
robotkernel/resources/notebooks/tutorial/DateLibrary.ipynb
robotkernel/resources/notebooks/tutorial/SeleniumKeywords.ipynb
robotkernel/resources/simmerjs/LICENSE
robotkernel/resources/simmerjs/simmer.js
robotkernel/resources/starter/quickstart-starter.ipynb
robotkernel/resources/starter/robotkernel-starter.json
robotkernel-1.6.data/data/etc/jupyter/jupyter_notebook_config.d/robotkernel-starter.json
robotkernel-1.6.dist-info/LICENSE
robotkernel-1.6.dist-info/METADATA
robotkernel-1.6.dist-info/WHEEL
robotkernel-1.6.dist-info/entry_points.txt
robotkernel-1.6.dist-info/top_level.txt
robotkernel-1.6.dist-info/RECORD
