Metadata-Version: 2.1
Name: robotkernel
Version: 1.6
Summary: A Jupyter kernel for interactive acceptance-test-driven development with the Robot Framework
Home-page: https://github.com/robots-from-jupyter/robotkernel
Author: Asko Soukka
Author-email: asko.soukka@iki.fi
License: BSD-3-Clause
Keywords: Interactive,Interpreter,Shell,Testing,Web
Platform: UNKNOWN
Classifier: Framework :: Jupyter
Classifier: Framework :: Robot Framework
Classifier: Framework :: Robot Framework :: Tool
Classifier: Intended Audience :: Developers
Classifier: Intended Audience :: Information Technology
Classifier: License :: OSI Approved :: BSD License
Classifier: Programming Language :: Python
Classifier: Programming Language :: Python :: 3.6
Classifier: Programming Language :: Python :: 3.7
Classifier: Programming Language :: Python :: 3 :: Only
Classifier: Topic :: Software Development :: Quality Assurance
Classifier: Topic :: Software Development :: Testing
Requires-Dist: docutils
Requires-Dist: ipykernel
Requires-Dist: ipywidgets
Requires-Dist: lunr
Requires-Dist: nbformat
Requires-Dist: pillow
Requires-Dist: pygments
Requires-Dist: robotframework (!=3.2a1,>=3.1)
Requires-Dist: setuptools
